setup.py
namataa_distributions_probability/Binomialdistribution.py
namataa_distributions_probability/Gaussiandistribution.py
namataa_distributions_probability/Generaldistribution.py
namataa_distributions_probability/__init__.py
namataa_distributions_probability.egg-info/PKG-INFO
namataa_distributions_probability.egg-info/SOURCES.txt
namataa_distributions_probability.egg-info/dependency_links.txt
namataa_distributions_probability.egg-info/not-zip-safe
namataa_distributions_probability.egg-info/top_level.txt